aiv_logging/__init__.py
aiv_logging/aiv_logging.py
aiv_logging/aivn_logger.py
aiv_logging-0.1.0.dist-info/METADATA
aiv_logging-0.1.0.dist-info/WHEEL
aiv_logging-0.1.0.dist-info/top_level.txt
aiv_logging-0.1.0.dist-info/RECORD
