Metadata-Version: 2.1
Name: aiv-logging
Version: 0.1.0
Summary: Aiv_logging make by AI Academy Viet Nam
Home-page: UNKNOWN
Author: Toan Silver
Author-email: ngoctoan1105@email.com
License: UNKNOWN
Keywords: python,aiv,logging
Platform: UNKNOWN
Classifier: Development Status :: 3 - Alpha
Classifier: Intended Audience :: Education
Classifier: Programming Language :: Python :: 3
Classifier: Operating System :: MacOS :: MacOS X
Classifier: Operating System :: Microsoft :: Windows
Requires-Dist: colorlog
